stayactive/__init__.py
stayactive/__main__.py
stayactive-1.0.1.dist-info/licenses/LICENSE
stayactive-1.0.1.dist-info/METADATA
stayactive-1.0.1.dist-info/WHEEL
stayactive-1.0.1.dist-info/entry_points.txt
stayactive-1.0.1.dist-info/top_level.txt
stayactive-1.0.1.dist-info/RECORD
