Metadata-Version: 2.4
Name: stayactive
Version: 1.0.1
Summary: A smart activity simulator utility that keeps your computer active while respecting your actual usage
Author: Rajdeep Banik
Author-email: Rajdeep Banik <banik.rajdeep1056@gmail.com>
License: MIT License
Project-URL: Homepage, https://github.com/rajdeepbanik/stayactive
Project-URL: Repository, https://github.com/rajdeepbanik/stayactive
Project-URL: Issues, https://github.com/rajdeepbanik/stayactive/issues
Keywords: activity,simulator,automation,mouse,keyboard,stay-active
Classifier: Development Status :: 4 - Beta
Classifier: Intended Audience :: End Users/Desktop
Classifier: License :: OSI Approved :: MIT License
Classifier: Operating System :: OS Independent
Classifier: Programming Language :: Python :: 3
Classifier: Programming Language :: Python :: 3.6
Classifier: Programming Language :: Python :: 3.7
Classifier: Programming Language :: Python :: 3.8
Classifier: Programming Language :: Python :: 3.9
Classifier: Programming Language :: Python :: 3.10
Classifier: Programming Language :: Python :: 3.11
Classifier: Programming Language :: Python :: 3.12
Classifier: Topic :: System :: Monitoring
Classifier: Topic :: Utilities
Requires-Python: >=3.6
License-File: LICENSE
Requires-Dist: pyautogui
Requires-Dist: pynput
Dynamic: author
Dynamic: license-file
Dynamic: requires-python
